jsonlog/__init__.py
jsonlog/config.py
jsonlog/formatter.py
jsonlog/tests/__init__.py
jsonlog/tests/capture.py
jsonlog/tests/conftest.py
jsonlog/tests/records.py
jsonlog/tests/test_config.py
jsonlog/tests/test_formatter.py
jsonlog-4.0.0.dist-info/WHEEL
jsonlog-4.0.0.dist-info/METADATA
jsonlog-4.0.0.dist-info/RECORD
