Metadata-Version: 2.1
Name: jsonlog
Version: 4.0.0
Summary: JSON formatter for the builtin logging module
Home-page: https://github.com/borntyping/jsonlog/tree/master/jsonlog
License: MIT
Author: Sam Clements
Author-email: sam@borntyping.co.uk
Requires-Python: >=3.6,<4.0
Classifier: License :: OSI Approved :: MIT License
Classifier: Programming Language :: Python :: 3
Classifier: Programming Language :: Python :: 3.6
Classifier: Programming Language :: Python :: 3.7
Classifier: Programming Language :: Python :: 3.8
Project-URL: Repository, https://github.com/borntyping/jsonlog
